bell_yespower.cp36-win32.pyd
bell_yespower-1.0.3.dist-info/METADATA
bell_yespower-1.0.3.dist-info/WHEEL
bell_yespower-1.0.3.dist-info/top_level.txt
bell_yespower-1.0.3.dist-info/RECORD
