Metadata-Version: 2.1
Name: bell-yespower
Version: 1.0.3
Summary: Bindings for yespower-1.0 proof of work used by bellcoin
Home-page: https://github.com/bellcoin-electrum/bell_yespower_python3
Author: y-chan
Author-email: yuto_tetuota@yahoo.co.jp
License: UNKNOWN
Platform: UNKNOWN
